kodo/quantities/__init__.py
kodo/quantities/py.typed
kodo_quantities-0.1.1.dist-info/WHEEL
kodo_quantities-0.1.1.dist-info/METADATA
kodo_quantities-0.1.1.dist-info/RECORD
