Metadata-Version: 2.1
Name: kodo.quantities
Version: 0.1.1
Summary: Types for representing physical quantities, which have a magnitude and a unit
Author-email: Dom Sekotill <dom.sekotill@kodo.org.uk>
Requires-Python: ~=3.11
Classifier: Development Status :: 4 - Beta
Classifier: Intended Audience :: Developers
Classifier: License :: OSI Approved :: Apache Software License
Classifier: Programming Language :: Python :: 3.11
Classifier: Programming Language :: Python :: 3.12
Classifier: Typing :: Typed
Project-URL: Issues, https://code.kodo.org.uk/dom/python-quantities/-/issues
Project-URL: Source, https://code.kodo.org.uk/dom/python-quantities
